MANIFEST.in
README.rst
requirements.txt
setup.cfg
setup.py
TopcoderDl/__init__.py
TopcoderDl/main.py
topcoder_dl.egg-info/PKG-INFO
topcoder_dl.egg-info/SOURCES.txt
topcoder_dl.egg-info/dependency_links.txt
topcoder_dl.egg-info/entry_points.txt
topcoder_dl.egg-info/pbr.json
topcoder_dl.egg-info/requires.txt
topcoder_dl.egg-info/top_level.txt