Metadata-Version: 1.1
Name: topcoder-dl
Version: 0.0.3
Summary: Downloads all TopCoder data-science tutorials and save as PDF
Home-page: https://github.com/tushar-rishav/topcoder-dl/
Author: Tushar Gautam
Author-email: tushar.rishav@gmail.com
License: GNU General Public License v3 (GPLv3)
Keywords: pdf,algorithms,tutorials,Topcoder,python,scrapping
Platform: UNKNOWN
Classifier: Operating System :: POSIX :: Linux
Classifier: Programming Language :: Python
Classifier: Programming Language :: Python :: 2.7
Classifier: Topic :: System :: Monitoring
